setup.py
bin/remns
remns/__init__.py
remns/admin_endpoints.py
remns/config.py
remns/db.py
remns/endpoints.py
remns/main.py
remns/models.py
remns.egg-info/PKG-INFO
remns.egg-info/SOURCES.txt
remns.egg-info/dependency_links.txt
remns.egg-info/requires.txt
remns.egg-info/top_level.txt
remns/dist/
remns/dist/static
remns/dist/templates
remns/dist/static/admin
remns/dist/static/admin/admin.css
remns/dist/static/admin/admin.js
remns/dist/static/admin/epiceditor
remns/dist/static/admin/utils.js
remns/dist/static/admin/epiceditor/base
remns/dist/static/admin/epiceditor/editor
remns/dist/static/admin/epiceditor/preview
remns/dist/static/admin/epiceditor/base/epiceditor.css
remns/dist/static/admin/epiceditor/editor/epic-dark.css
remns/dist/static/admin/epiceditor/editor/epic-light.css
remns/dist/static/admin/epiceditor/preview/bartik.css
remns/dist/static/admin/epiceditor/preview/github.css
remns/dist/static/admin/epiceditor/preview/preview-dark.css
remns/dist/templates/admin
remns/dist/templates/admin/all_posts.html
remns/dist/templates/admin/base.html
remns/dist/templates/admin/edit_view.html
remns/dist/templates/admin/login.html
remns/tests/__init__.py