Metadata-Version: 1.1
Name: remns
Version: 0.1.0.dev4
Summary: An elegant Python blogging engine.
Home-page: https://github.com/vchynarov/remns
Author: Viktor Chynarov
Author-email: viktor.chynarov@gmail.com
License: MIT
Keywords: blog sqlalchemy werkzeug engine web framework
Platform: UNKNOWN
Classifier: Development Status :: 3 - Alpha
Classifier: Intended Audience :: Developers
Classifier: License :: OSI Approved :: MIT License
Classifier: Programming Language :: Python :: 2.7
